setup.cfg
setup.py
version.py
xonfig.py
test/test1.py
test/test2.py
test/test3.py
test/test4.py
xonfig.egg-info/PKG-INFO
xonfig.egg-info/SOURCES.txt
xonfig.egg-info/dependency_links.txt
xonfig.egg-info/top_level.txt