Metadata-Version: 1.0
Name: xonfig
Version: 1.0.1
Summary: Python configparser wrapper
Home-page: https://github.com/talhasch/xonfig
Author: Talha Buğra Bulut
Author-email: talhabugrabulut@gmail.com
License: UNKNOWN
Keywords: config,parser,configparser
Platform: UNKNOWN
